{
  "version": "1.0",
  "workerIdList": [
    -1,
    2,
    0,
    1
  ],
  "metrics": [
    {
      "type": "build_line",
      "endTime": 1700789802644,
      "status": "closed",
      "children": [],
      "name": "overallTime",
      "taskName": "default@PreBuild",
      "taskPath": "entry",
      "workerId": -1,
      "startTime": 1700789802643
    },
    {
      "type": "build_line",
      "endTime": 1700789802648,
      "status": "closed",
      "children": [],
      "name": "overallTime",
      "taskName": "default@PreBuild",
      "taskPath": "common_lib",
      "workerId": -1,
      "startTime": 1700789802647
    },
    {
      "type": "build_line",
      "endTime": 1700789802651,
      "status": "closed",
      "children": [],
      "name": "overallTime",
      "taskName": "default@GenerateMetadata",
      "taskPath": "entry",
      "workerId": -1,
      "startTime": 1700789802649
    },
    {
      "type": "build_line",
      "endTime": 1700789802655,
      "status": "closed",
      "children": [],
      "name": "overallTime",
      "taskName": "default@BuildNativeWithCmake",
      "taskPath": "entry",
      "workerId": -1,
      "startTime": 1700789802655
    },
    {
      "type": "build_line",
      "endTime": 1700789802656,
      "status": "closed",
      "children": [],
      "name": "overallTime",
      "taskName": "default@GenerateLoaderJson",
      "taskPath": "entry",
      "workerId": -1,
      "startTime": 1700789802656
    },
    {
      "type": "build_line",
      "endTime": 1700789802656,
      "status": "closed",
      "children": [],
      "name": "overallTime",
      "taskName": "default@BuildNativeWithCmake",
      "taskPath": "common_lib",
      "workerId": -1,
      "startTime": 1700789802656
    },
    {
      "type": "build_line",
      "endTime": 1700789802658,
      "status": "closed",
      "children": [],
      "name": "overallTime",
      "taskName": "default@MergeProfile",
      "taskPath": "common_lib",
      "workerId": -1,
      "startTime": 1700789802658
    },
    {
      "type": "build_line",
      "endTime": 1700789802659,
      "status": "closed",
      "children": [],
      "name": "overallTime",
      "taskName": "default@BuildNativeWithNinja",
      "taskPath": "entry",
      "workerId": -1,
      "startTime": 1700789802658
    },
    {
      "type": "build_line",
      "endTime": 1700789802659,
      "status": "closed",
      "children": [],
      "name": "overallTime",
      "taskName": "default@BuildNativeWithNinja",
      "taskPath": "common_lib",
      "workerId": -1,
      "startTime": 1700789802659
    },
    {
      "type": "build_line",
      "endTime": 1700789802661,
      "status": "closed",
      "children": [],
      "name": "overallTime",
      "taskName": "default@MergeProfile",
      "taskPath": "entry",
      "workerId": -1,
      "startTime": 1700789802661
    },
    {
      "type": "build_line",
      "endTime": 1700789802663,
      "status": "closed",
      "children": [],
      "name": "overallTime",
      "taskName": "default@ProcessLibs",
      "taskPath": "common_lib",
      "workerId": -1,
      "startTime": 1700789802662
    },
    {
      "type": "build_line",
      "endTime": 1700789802667,
      "status": "closed",
      "children": [],
      "name": "overallTime",
      "taskName": "default@MakePackInfo",
      "taskPath": "entry",
      "workerId": -1,
      "startTime": 1700789802664
    },
    {
      "type": "build_line",
      "endTime": 1700789802668,
      "status": "closed",
      "children": [],
      "name": "overallTime",
      "taskName": "default@ProcessProfile",
      "taskPath": "entry",
      "workerId": -1,
      "startTime": 1700789802668
    },
    {
      "type": "build_line",
      "endTime": 1700789802670,
      "status": "closed",
      "children": [],
      "name": "overallTime",
      "taskName": "default@ProcessLibs",
      "taskPath": "entry",
      "workerId": -1,
      "startTime": 1700789802669
    },
    {
      "type": "build_line",
      "endTime": 1700789802671,
      "status": "closed",
      "children": [],
      "name": "overallTime",
      "taskName": "default@ProcessResource",
      "taskPath": "entry",
      "workerId": -1,
      "startTime": 1700789802670
    },
    {
      "type": "build_line",
      "endTime": 1700789802762,
      "status": "closed",
      "children": [],
      "name": "overallTime",
      "taskName": "default@CompileResource",
      "taskPath": "entry",
      "workerId": -1,
      "startTime": 1700789802671
    },
    {
      "type": "build_line",
      "endTime": 1700789802771,
      "status": "closed",
      "children": [],
      "name": "overallTime",
      "taskName": "default@CompileJS",
      "taskPath": "entry",
      "workerId": -1,
      "startTime": 1700789802770
    },
    {
      "type": "build_line",
      "endTime": 1700789805354,
      "status": "closed",
      "children": [],
      "name": "overallTime",
      "taskName": "default@CompileArkTS",
      "taskPath": "entry",
      "workerId": 2,
      "startTime": 1700789802770
    },
    {
      "type": "default",
      "endTime": 1700789805354,
      "status": "closed",
      "children": [
        {
          "type": "build_line",
          "endTime": 1700789805354,
          "status": "closed",
          "children": [],
          "name": "overallTime",
          "taskName": "default@CompileArkTS",
          "taskPath": "entry",
          "workerId": 2,
          "startTime": 1700789802770
        }
      ],
      "name": "overallTime",
      "taskName": "default@CompileArkTS",
      "taskPath": "entry",
      "workerId": -1,
      "startTime": 1700789802763
    },
    {
      "type": "build_line",
      "endTime": 1700789814271,
      "status": "closed",
      "children": [],
      "name": "overallTime",
      "taskName": "default@PreBuild",
      "taskPath": "entry",
      "workerId": -1,
      "startTime": 1700789814270
    },
    {
      "type": "build_line",
      "endTime": 1700789814273,
      "status": "closed",
      "children": [],
      "name": "overallTime",
      "taskName": "default@PreBuild",
      "taskPath": "common_lib",
      "workerId": -1,
      "startTime": 1700789814272
    },
    {
      "type": "build_line",
      "endTime": 1700789814276,
      "status": "closed",
      "children": [],
      "name": "overallTime",
      "taskName": "default@GenerateMetadata",
      "taskPath": "entry",
      "workerId": -1,
      "startTime": 1700789814274
    },
    {
      "type": "build_line",
      "endTime": 1700789814279,
      "status": "closed",
      "children": [],
      "name": "overallTime",
      "taskName": "default@BuildNativeWithCmake",
      "taskPath": "entry",
      "workerId": -1,
      "startTime": 1700789814279
    },
    {
      "type": "build_line",
      "endTime": 1700789814280,
      "status": "closed",
      "children": [],
      "name": "overallTime",
      "taskName": "default@GenerateLoaderJson",
      "taskPath": "entry",
      "workerId": -1,
      "startTime": 1700789814279
    },
    {
      "type": "build_line",
      "endTime": 1700789814281,
      "status": "closed",
      "children": [],
      "name": "overallTime",
      "taskName": "default@BuildNativeWithCmake",
      "taskPath": "common_lib",
      "workerId": -1,
      "startTime": 1700789814281
    },
    {
      "type": "build_line",
      "endTime": 1700789814282,
      "status": "closed",
      "children": [],
      "name": "overallTime",
      "taskName": "default@MergeProfile",
      "taskPath": "common_lib",
      "workerId": -1,
      "startTime": 1700789814282
    },
    {
      "type": "build_line",
      "endTime": 1700789814282,
      "status": "closed",
      "children": [],
      "name": "overallTime",
      "taskName": "default@BuildNativeWithNinja",
      "taskPath": "entry",
      "workerId": -1,
      "startTime": 1700789814282
    },
    {
      "type": "build_line",
      "endTime": 1700789814284,
      "status": "closed",
      "children": [],
      "name": "overallTime",
      "taskName": "default@BuildNativeWithNinja",
      "taskPath": "common_lib",
      "workerId": -1,
      "startTime": 1700789814284
    },
    {
      "type": "build_line",
      "endTime": 1700789814285,
      "status": "closed",
      "children": [],
      "name": "overallTime",
      "taskName": "default@MergeProfile",
      "taskPath": "entry",
      "workerId": -1,
      "startTime": 1700789814285
    },
    {
      "type": "build_line",
      "endTime": 1700789814286,
      "status": "closed",
      "children": [],
      "name": "overallTime",
      "taskName": "default@ProcessLibs",
      "taskPath": "common_lib",
      "workerId": -1,
      "startTime": 1700789814285
    },
    {
      "type": "build_line",
      "endTime": 1700789814289,
      "status": "closed",
      "children": [],
      "name": "overallTime",
      "taskName": "default@MakePackInfo",
      "taskPath": "entry",
      "workerId": -1,
      "startTime": 1700789814287
    },
    {
      "type": "build_line",
      "endTime": 1700789814291,
      "status": "closed",
      "children": [],
      "name": "overallTime",
      "taskName": "default@ProcessProfile",
      "taskPath": "entry",
      "workerId": -1,
      "startTime": 1700789814291
    },
    {
      "type": "build_line",
      "endTime": 1700789814292,
      "status": "closed",
      "children": [],
      "name": "overallTime",
      "taskName": "default@ProcessLibs",
      "taskPath": "entry",
      "workerId": -1,
      "startTime": 1700789814291
    },
    {
      "type": "build_line",
      "endTime": 1700789814296,
      "status": "closed",
      "children": [],
      "name": "overallTime",
      "taskName": "default@ProcessResource",
      "taskPath": "entry",
      "workerId": -1,
      "startTime": 1700789814293
    },
    {
      "type": "build_line",
      "endTime": 1700789814299,
      "status": "closed",
      "children": [],
      "name": "overallTime",
      "taskName": "default@CompileResource",
      "taskPath": "entry",
      "workerId": -1,
      "startTime": 1700789814296
    },
    {
      "type": "build_line",
      "endTime": 1700789814308,
      "status": "closed",
      "children": [],
      "name": "overallTime",
      "taskName": "default@CompileJS",
      "taskPath": "entry",
      "workerId": -1,
      "startTime": 1700789814306
    },
    {
      "type": "build_line",
      "endTime": 1700789817812,
      "status": "closed",
      "children": [],
      "name": "overallTime",
      "taskName": "default@CompileArkTS",
      "taskPath": "entry",
      "workerId": 0,
      "startTime": 1700789814306
    },
    {
      "type": "default",
      "endTime": 1700789817812,
      "status": "closed",
      "children": [
        {
          "type": "build_line",
          "endTime": 1700789817812,
          "status": "closed",
          "children": [],
          "name": "overallTime",
          "taskName": "default@CompileArkTS",
          "taskPath": "entry",
          "workerId": 0,
          "startTime": 1700789814306
        }
      ],
      "name": "overallTime",
      "taskName": "default@CompileArkTS",
      "taskPath": "entry",
      "workerId": -1,
      "startTime": 1700789814299
    },
    {
      "type": "build_line",
      "endTime": 1700790127019,
      "status": "closed",
      "children": [],
      "name": "overallTime",
      "taskName": "default@PreBuild",
      "taskPath": "entry",
      "workerId": -1,
      "startTime": 1700790127019
    },
    {
      "type": "build_line",
      "endTime": 1700790127022,
      "status": "closed",
      "children": [],
      "name": "overallTime",
      "taskName": "default@PreBuild",
      "taskPath": "common_lib",
      "workerId": -1,
      "startTime": 1700790127021
    },
    {
      "type": "build_line",
      "endTime": 1700790127025,
      "status": "closed",
      "children": [],
      "name": "overallTime",
      "taskName": "default@GenerateMetadata",
      "taskPath": "entry",
      "workerId": -1,
      "startTime": 1700790127023
    },
    {
      "type": "build_line",
      "endTime": 1700790127027,
      "status": "closed",
      "children": [],
      "name": "overallTime",
      "taskName": "default@BuildNativeWithCmake",
      "taskPath": "entry",
      "workerId": -1,
      "startTime": 1700790127027
    },
    {
      "type": "build_line",
      "endTime": 1700790127029,
      "status": "closed",
      "children": [],
      "name": "overallTime",
      "taskName": "default@GenerateLoaderJson",
      "taskPath": "entry",
      "workerId": -1,
      "startTime": 1700790127029
    },
    {
      "type": "build_line",
      "endTime": 1700790127029,
      "status": "closed",
      "children": [],
      "name": "overallTime",
      "taskName": "default@BuildNativeWithCmake",
      "taskPath": "common_lib",
      "workerId": -1,
      "startTime": 1700790127029
    },
    {
      "type": "build_line",
      "endTime": 1700790127031,
      "status": "closed",
      "children": [],
      "name": "overallTime",
      "taskName": "default@MergeProfile",
      "taskPath": "common_lib",
      "workerId": -1,
      "startTime": 1700790127031
    },
    {
      "type": "build_line",
      "endTime": 1700790127032,
      "status": "closed",
      "children": [],
      "name": "overallTime",
      "taskName": "default@BuildNativeWithNinja",
      "taskPath": "entry",
      "workerId": -1,
      "startTime": 1700790127032
    },
    {
      "type": "build_line",
      "endTime": 1700790127033,
      "status": "closed",
      "children": [],
      "name": "overallTime",
      "taskName": "default@BuildNativeWithNinja",
      "taskPath": "common_lib",
      "workerId": -1,
      "startTime": 1700790127032
    },
    {
      "type": "build_line",
      "endTime": 1700790127034,
      "status": "closed",
      "children": [],
      "name": "overallTime",
      "taskName": "default@MergeProfile",
      "taskPath": "entry",
      "workerId": -1,
      "startTime": 1700790127034
    },
    {
      "type": "build_line",
      "endTime": 1700790127035,
      "status": "closed",
      "children": [],
      "name": "overallTime",
      "taskName": "default@ProcessLibs",
      "taskPath": "common_lib",
      "workerId": -1,
      "startTime": 1700790127034
    },
    {
      "type": "build_line",
      "endTime": 1700790127039,
      "status": "closed",
      "children": [],
      "name": "overallTime",
      "taskName": "default@MakePackInfo",
      "taskPath": "entry",
      "workerId": -1,
      "startTime": 1700790127036
    },
    {
      "type": "build_line",
      "endTime": 1700790127041,
      "status": "closed",
      "children": [],
      "name": "overallTime",
      "taskName": "default@ProcessProfile",
      "taskPath": "entry",
      "workerId": -1,
      "startTime": 1700790127041
    },
    {
      "type": "build_line",
      "endTime": 1700790127043,
      "status": "closed",
      "children": [],
      "name": "overallTime",
      "taskName": "default@ProcessLibs",
      "taskPath": "entry",
      "workerId": -1,
      "startTime": 1700790127042
    },
    {
      "type": "build_line",
      "endTime": 1700790127044,
      "status": "closed",
      "children": [],
      "name": "overallTime",
      "taskName": "default@ProcessResource",
      "taskPath": "entry",
      "workerId": -1,
      "startTime": 1700790127043
    },
    {
      "type": "build_line",
      "endTime": 1700790127047,
      "status": "closed",
      "children": [],
      "name": "overallTime",
      "taskName": "default@CompileResource",
      "taskPath": "entry",
      "workerId": -1,
      "startTime": 1700790127044
    },
    {
      "type": "build_line",
      "endTime": 1700790127054,
      "status": "closed",
      "children": [],
      "name": "overallTime",
      "taskName": "default@CompileJS",
      "taskPath": "entry",
      "workerId": -1,
      "startTime": 1700790127053
    },
    {
      "type": "build_line",
      "endTime": 1700790130420,
      "status": "closed",
      "children": [],
      "name": "overallTime",
      "taskName": "default@CompileArkTS",
      "taskPath": "entry",
      "workerId": 0,
      "startTime": 1700790127053
    },
    {
      "type": "default",
      "endTime": 1700790130420,
      "status": "closed",
      "children": [
        {
          "type": "build_line",
          "endTime": 1700790130420,
          "status": "closed",
          "children": [],
          "name": "overallTime",
          "taskName": "default@CompileArkTS",
          "taskPath": "entry",
          "workerId": 0,
          "startTime": 1700790127053
        }
      ],
      "name": "overallTime",
      "taskName": "default@CompileArkTS",
      "taskPath": "entry",
      "workerId": -1,
      "startTime": 1700790127047
    },
    {
      "type": "build_line",
      "endTime": 1700791618468,
      "status": "closed",
      "children": [],
      "name": "overallTime",
      "taskName": "default@PreBuild",
      "taskPath": "entry",
      "workerId": -1,
      "startTime": 1700791618468
    },
    {
      "type": "build_line",
      "endTime": 1700791618471,
      "status": "closed",
      "children": [],
      "name": "overallTime",
      "taskName": "default@PreBuild",
      "taskPath": "common_lib",
      "workerId": -1,
      "startTime": 1700791618471
    },
    {
      "type": "build_line",
      "endTime": 1700791618477,
      "status": "closed",
      "children": [],
      "name": "overallTime",
      "taskName": "default@GenerateMetadata",
      "taskPath": "entry",
      "workerId": -1,
      "startTime": 1700791618475
    },
    {
      "type": "build_line",
      "endTime": 1700791618479,
      "status": "closed",
      "children": [],
      "name": "overallTime",
      "taskName": "default@BuildNativeWithCmake",
      "taskPath": "entry",
      "workerId": -1,
      "startTime": 1700791618479
    },
    {
      "type": "build_line",
      "endTime": 1700791618480,
      "status": "closed",
      "children": [],
      "name": "overallTime",
      "taskName": "default@GenerateLoaderJson",
      "taskPath": "entry",
      "workerId": -1,
      "startTime": 1700791618480
    },
    {
      "type": "build_line",
      "endTime": 1700791618482,
      "status": "closed",
      "children": [],
      "name": "overallTime",
      "taskName": "default@BuildNativeWithCmake",
      "taskPath": "common_lib",
      "workerId": -1,
      "startTime": 1700791618482
    },
    {
      "type": "build_line",
      "endTime": 1700791618483,
      "status": "closed",
      "children": [],
      "name": "overallTime",
      "taskName": "default@MergeProfile",
      "taskPath": "common_lib",
      "workerId": -1,
      "startTime": 1700791618483
    },
    {
      "type": "build_line",
      "endTime": 1700791618484,
      "status": "closed",
      "children": [],
      "name": "overallTime",
      "taskName": "default@BuildNativeWithNinja",
      "taskPath": "entry",
      "workerId": -1,
      "startTime": 1700791618484
    },
    {
      "type": "build_line",
      "endTime": 1700791618485,
      "status": "closed",
      "children": [],
      "name": "overallTime",
      "taskName": "default@BuildNativeWithNinja",
      "taskPath": "common_lib",
      "workerId": -1,
      "startTime": 1700791618485
    },
    {
      "type": "build_line",
      "endTime": 1700791618487,
      "status": "closed",
      "children": [],
      "name": "overallTime",
      "taskName": "default@MergeProfile",
      "taskPath": "entry",
      "workerId": -1,
      "startTime": 1700791618487
    },
    {
      "type": "build_line",
      "endTime": 1700791618487,
      "status": "closed",
      "children": [],
      "name": "overallTime",
      "taskName": "default@ProcessLibs",
      "taskPath": "common_lib",
      "workerId": -1,
      "startTime": 1700791618487
    },
    {
      "type": "build_line",
      "endTime": 1700791618491,
      "status": "closed",
      "children": [],
      "name": "overallTime",
      "taskName": "default@MakePackInfo",
      "taskPath": "entry",
      "workerId": -1,
      "startTime": 1700791618488
    },
    {
      "type": "build_line",
      "endTime": 1700791618492,
      "status": "closed",
      "children": [],
      "name": "overallTime",
      "taskName": "default@ProcessProfile",
      "taskPath": "entry",
      "workerId": -1,
      "startTime": 1700791618492
    },
    {
      "type": "build_line",
      "endTime": 1700791618492,
      "status": "closed",
      "children": [],
      "name": "overallTime",
      "taskName": "default@ProcessLibs",
      "taskPath": "entry",
      "workerId": -1,
      "startTime": 1700791618492
    },
    {
      "type": "build_line",
      "endTime": 1700791618494,
      "status": "closed",
      "children": [],
      "name": "overallTime",
      "taskName": "default@ProcessResource",
      "taskPath": "entry",
      "workerId": -1,
      "startTime": 1700791618493
    },
    {
      "type": "build_line",
      "endTime": 1700791618498,
      "status": "closed",
      "children": [],
      "name": "overallTime",
      "taskName": "default@CompileResource",
      "taskPath": "entry",
      "workerId": -1,
      "startTime": 1700791618494
    },
    {
      "type": "build_line",
      "endTime": 1700791618504,
      "status": "closed",
      "children": [],
      "name": "overallTime",
      "taskName": "default@CompileJS",
      "taskPath": "entry",
      "workerId": -1,
      "startTime": 1700791618503
    },
    {
      "type": "build_line",
      "endTime": 1700791621386,
      "status": "closed",
      "children": [],
      "name": "overallTime",
      "taskName": "default@CompileArkTS",
      "taskPath": "entry",
      "workerId": 0,
      "startTime": 1700791618502
    },
    {
      "type": "default",
      "endTime": 1700791621386,
      "status": "closed",
      "children": [
        {
          "type": "build_line",
          "endTime": 1700791621386,
          "status": "closed",
          "children": [],
          "name": "overallTime",
          "taskName": "default@CompileArkTS",
          "taskPath": "entry",
          "workerId": 0,
          "startTime": 1700791618502
        }
      ],
      "name": "overallTime",
      "taskName": "default@CompileArkTS",
      "taskPath": "entry",
      "workerId": -1,
      "startTime": 1700791618498
    },
    {
      "type": "build_line",
      "endTime": 1700791621830,
      "status": "closed",
      "children": [],
      "name": "overallTime",
      "taskName": "default@PackageHap",
      "taskPath": "entry",
      "workerId": 1,
      "startTime": 1700791621390
    },
    {
      "type": "default",
      "endTime": 1700791621830,
      "status": "closed",
      "children": [
        {
          "type": "build_line",
          "endTime": 1700791621830,
          "status": "closed",
          "children": [],
          "name": "overallTime",
          "taskName": "default@PackageHap",
          "taskPath": "entry",
          "workerId": 1,
          "startTime": 1700791621390
        }
      ],
      "name": "overallTime",
      "taskName": "default@PackageHap",
      "taskPath": "entry",
      "workerId": -1,
      "startTime": 1700791621388
    },
    {
      "type": "build_line",
      "endTime": 1700791621831,
      "status": "closed",
      "children": [],
      "name": "overallTime",
      "taskName": "default@SignHap",
      "taskPath": "entry",
      "workerId": -1,
      "startTime": 1700791621830
    },
    {
      "type": "build_line",
      "endTime": 1700791621831,
      "status": "closed",
      "children": [],
      "name": "overallTime",
      "taskName": "assembleHap",
      "taskPath": "entry",
      "workerId": -1,
      "startTime": 1700791621831
    },
    {
      "type": "build_line",
      "endTime": 1700791959538,
      "status": "closed",
      "children": [],
      "name": "overallTime",
      "taskName": "default@PreBuild",
      "taskPath": "entry",
      "workerId": -1,
      "startTime": 1700791959538
    },
    {
      "type": "build_line",
      "endTime": 1700791959540,
      "status": "closed",
      "children": [],
      "name": "overallTime",
      "taskName": "default@PreBuild",
      "taskPath": "common_lib",
      "workerId": -1,
      "startTime": 1700791959539
    },
    {
      "type": "build_line",
      "endTime": 1700791959543,
      "status": "closed",
      "children": [],
      "name": "overallTime",
      "taskName": "default@GenerateMetadata",
      "taskPath": "entry",
      "workerId": -1,
      "startTime": 1700791959541
    },
    {
      "type": "build_line",
      "endTime": 1700791959546,
      "status": "closed",
      "children": [],
      "name": "overallTime",
      "taskName": "default@BuildNativeWithCmake",
      "taskPath": "entry",
      "workerId": -1,
      "startTime": 1700791959546
    },
    {
      "type": "build_line",
      "endTime": 1700791959547,
      "status": "closed",
      "children": [],
      "name": "overallTime",
      "taskName": "default@GenerateLoaderJson",
      "taskPath": "entry",
      "workerId": -1,
      "startTime": 1700791959547
    },
    {
      "type": "build_line",
      "endTime": 1700791959548,
      "status": "closed",
      "children": [],
      "name": "overallTime",
      "taskName": "default@BuildNativeWithCmake",
      "taskPath": "common_lib",
      "workerId": -1,
      "startTime": 1700791959548
    },
    {
      "type": "build_line",
      "endTime": 1700791959550,
      "status": "closed",
      "children": [],
      "name": "overallTime",
      "taskName": "default@MergeProfile",
      "taskPath": "common_lib",
      "workerId": -1,
      "startTime": 1700791959550
    },
    {
      "type": "build_line",
      "endTime": 1700791959551,
      "status": "closed",
      "children": [],
      "name": "overallTime",
      "taskName": "default@BuildNativeWithNinja",
      "taskPath": "entry",
      "workerId": -1,
      "startTime": 1700791959551
    },
    {
      "type": "build_line",
      "endTime": 1700791959553,
      "status": "closed",
      "children": [],
      "name": "overallTime",
      "taskName": "default@BuildNativeWithNinja",
      "taskPath": "common_lib",
      "workerId": -1,
      "startTime": 1700791959553
    },
    {
      "type": "build_line",
      "endTime": 1700791959554,
      "status": "closed",
      "children": [],
      "name": "overallTime",
      "taskName": "default@MergeProfile",
      "taskPath": "entry",
      "workerId": -1,
      "startTime": 1700791959554
    },
    {
      "type": "build_line",
      "endTime": 1700791959556,
      "status": "closed",
      "children": [],
      "name": "overallTime",
      "taskName": "default@ProcessLibs",
      "taskPath": "common_lib",
      "workerId": -1,
      "startTime": 1700791959555
    },
    {
      "type": "build_line",
      "endTime": 1700791959558,
      "status": "closed",
      "children": [],
      "name": "overallTime",
      "taskName": "default@MakePackInfo",
      "taskPath": "entry",
      "workerId": -1,
      "startTime": 1700791959556
    },
    {
      "type": "build_line",
      "endTime": 1700791959559,
      "status": "closed",
      "children": [],
      "name": "overallTime",
      "taskName": "default@ProcessProfile",
      "taskPath": "entry",
      "workerId": -1,
      "startTime": 1700791959559
    },
    {
      "type": "build_line",
      "endTime": 1700791959560,
      "status": "closed",
      "children": [],
      "name": "overallTime",
      "taskName": "default@ProcessLibs",
      "taskPath": "entry",
      "workerId": -1,
      "startTime": 1700791959560
    },
    {
      "type": "build_line",
      "endTime": 1700791959562,
      "status": "closed",
      "children": [],
      "name": "overallTime",
      "taskName": "default@ProcessResource",
      "taskPath": "entry",
      "workerId": -1,
      "startTime": 1700791959561
    },
    {
      "type": "build_line",
      "endTime": 1700791959565,
      "status": "closed",
      "children": [],
      "name": "overallTime",
      "taskName": "default@CompileResource",
      "taskPath": "entry",
      "workerId": -1,
      "startTime": 1700791959562
    },
    {
      "type": "build_line",
      "endTime": 1700791959575,
      "status": "closed",
      "children": [],
      "name": "overallTime",
      "taskName": "default@CompileJS",
      "taskPath": "entry",
      "workerId": -1,
      "startTime": 1700791959573
    },
    {
      "type": "build_line",
      "endTime": 1700791961382,
      "status": "closed",
      "children": [],
      "name": "overallTime",
      "taskName": "default@CompileArkTS",
      "taskPath": "entry",
      "workerId": 0,
      "startTime": 1700791959672
    },
    {
      "type": "default",
      "endTime": 1700791961383,
      "status": "closed",
      "children": [
        {
          "type": "build_line",
          "endTime": 1700791961382,
          "status": "closed",
          "children": [],
          "name": "overallTime",
          "taskName": "default@CompileArkTS",
          "taskPath": "entry",
          "workerId": 0,
          "startTime": 1700791959672
        }
      ],
      "name": "overallTime",
      "taskName": "default@CompileArkTS",
      "taskPath": "entry",
      "workerId": -1,
      "startTime": 1700791959565
    },
    {
      "type": "build_line",
      "endTime": 1700791961567,
      "status": "closed",
      "children": [],
      "name": "overallTime",
      "taskName": "default@PackageHap",
      "taskPath": "entry",
      "workerId": 1,
      "startTime": 1700791961386
    },
    {
      "type": "default",
      "endTime": 1700791961567,
      "status": "closed",
      "children": [
        {
          "type": "build_line",
          "endTime": 1700791961567,
          "status": "closed",
          "children": [],
          "name": "overallTime",
          "taskName": "default@PackageHap",
          "taskPath": "entry",
          "workerId": 1,
          "startTime": 1700791961386
        }
      ],
      "name": "overallTime",
      "taskName": "default@PackageHap",
      "taskPath": "entry",
      "workerId": -1,
      "startTime": 1700791961384
    },
    {
      "type": "build_line",
      "endTime": 1700791961568,
      "status": "closed",
      "children": [],
      "name": "overallTime",
      "taskName": "default@SignHap",
      "taskPath": "entry",
      "workerId": -1,
      "startTime": 1700791961568
    },
    {
      "type": "build_line",
      "endTime": 1700791961569,
      "status": "closed",
      "children": [],
      "name": "overallTime",
      "taskName": "assembleHap",
      "taskPath": "entry",
      "workerId": -1,
      "startTime": 1700791961569
    },
    {
      "type": "build_line",
      "endTime": 1700793182426,
      "status": "closed",
      "children": [],
      "name": "overallTime",
      "taskName": "default@PreBuild",
      "taskPath": "entry",
      "workerId": -1,
      "startTime": 1700793182425
    },
    {
      "type": "build_line",
      "endTime": 1700793182430,
      "status": "closed",
      "children": [],
      "name": "overallTime",
      "taskName": "default@PreBuild",
      "taskPath": "common_lib",
      "workerId": -1,
      "startTime": 1700793182429
    },
    {
      "type": "build_line",
      "endTime": 1700793182440,
      "status": "closed",
      "children": [],
      "name": "overallTime",
      "taskName": "default@GenerateMetadata",
      "taskPath": "entry",
      "workerId": -1,
      "startTime": 1700793182434
    },
    {
      "type": "build_line",
      "endTime": 1700793182445,
      "status": "closed",
      "children": [],
      "name": "overallTime",
      "taskName": "default@BuildNativeWithCmake",
      "taskPath": "entry",
      "workerId": -1,
      "startTime": 1700793182445
    },
    {
      "type": "build_line",
      "endTime": 1700793182446,
      "status": "closed",
      "children": [],
      "name": "overallTime",
      "taskName": "default@GenerateLoaderJson",
      "taskPath": "entry",
      "workerId": -1,
      "startTime": 1700793182446
    },
    {
      "type": "build_line",
      "endTime": 1700793182446,
      "status": "closed",
      "children": [],
      "name": "overallTime",
      "taskName": "default@BuildNativeWithCmake",
      "taskPath": "common_lib",
      "workerId": -1,
      "startTime": 1700793182446
    },
    {
      "type": "build_line",
      "endTime": 1700793182448,
      "status": "closed",
      "children": [],
      "name": "overallTime",
      "taskName": "default@MergeProfile",
      "taskPath": "common_lib",
      "workerId": -1,
      "startTime": 1700793182447
    },
    {
      "type": "build_line",
      "endTime": 1700793182449,
      "status": "closed",
      "children": [],
      "name": "overallTime",
      "taskName": "default@BuildNativeWithNinja",
      "taskPath": "entry",
      "workerId": -1,
      "startTime": 1700793182449
    },
    {
      "type": "build_line",
      "endTime": 1700793182453,
      "status": "closed",
      "children": [],
      "name": "overallTime",
      "taskName": "default@BuildNativeWithNinja",
      "taskPath": "common_lib",
      "workerId": -1,
      "startTime": 1700793182452
    },
    {
      "type": "build_line",
      "endTime": 1700793182455,
      "status": "closed",
      "children": [],
      "name": "overallTime",
      "taskName": "default@MergeProfile",
      "taskPath": "entry",
      "workerId": -1,
      "startTime": 1700793182454
    },
    {
      "type": "build_line",
      "endTime": 1700793182455,
      "status": "closed",
      "children": [],
      "name": "overallTime",
      "taskName": "default@ProcessLibs",
      "taskPath": "common_lib",
      "workerId": -1,
      "startTime": 1700793182455
    },
    {
      "type": "build_line",
      "endTime": 1700793182460,
      "status": "closed",
      "children": [],
      "name": "overallTime",
      "taskName": "default@MakePackInfo",
      "taskPath": "entry",
      "workerId": -1,
      "startTime": 1700793182456
    },
    {
      "type": "build_line",
      "endTime": 1700793182462,
      "status": "closed",
      "children": [],
      "name": "overallTime",
      "taskName": "default@ProcessProfile",
      "taskPath": "entry",
      "workerId": -1,
      "startTime": 1700793182462
    },
    {
      "type": "build_line",
      "endTime": 1700793182463,
      "status": "closed",
      "children": [],
      "name": "overallTime",
      "taskName": "default@ProcessLibs",
      "taskPath": "entry",
      "workerId": -1,
      "startTime": 1700793182463
    },
    {
      "type": "build_line",
      "endTime": 1700793182465,
      "status": "closed",
      "children": [],
      "name": "overallTime",
      "taskName": "default@ProcessResource",
      "taskPath": "entry",
      "workerId": -1,
      "startTime": 1700793182463
    },
    {
      "type": "build_line",
      "endTime": 1700793182467,
      "status": "closed",
      "children": [],
      "name": "overallTime",
      "taskName": "default@CompileResource",
      "taskPath": "entry",
      "workerId": -1,
      "startTime": 1700793182465
    },
    {
      "type": "build_line",
      "endTime": 1700793182477,
      "status": "closed",
      "children": [],
      "name": "overallTime",
      "taskName": "default@CompileJS",
      "taskPath": "entry",
      "workerId": -1,
      "startTime": 1700793182475
    },
    {
      "type": "build_line",
      "endTime": 1700793184565,
      "status": "closed",
      "children": [],
      "name": "overallTime",
      "taskName": "default@CompileArkTS",
      "taskPath": "entry",
      "workerId": 0,
      "startTime": 1700793182574
    },
    {
      "type": "default",
      "endTime": 1700793184565,
      "status": "closed",
      "children": [
        {
          "type": "build_line",
          "endTime": 1700793184565,
          "status": "closed",
          "children": [],
          "name": "overallTime",
          "taskName": "default@CompileArkTS",
          "taskPath": "entry",
          "workerId": 0,
          "startTime": 1700793182574
        }
      ],
      "name": "overallTime",
      "taskName": "default@CompileArkTS",
      "taskPath": "entry",
      "workerId": -1,
      "startTime": 1700793182467
    },
    {
      "type": "build_line",
      "endTime": 1700793184749,
      "status": "closed",
      "children": [],
      "name": "overallTime",
      "taskName": "default@PackageHap",
      "taskPath": "entry",
      "workerId": 1,
      "startTime": 1700793184567
    },
    {
      "type": "default",
      "endTime": 1700793184749,
      "status": "closed",
      "children": [
        {
          "type": "build_line",
          "endTime": 1700793184749,
          "status": "closed",
          "children": [],
          "name": "overallTime",
          "taskName": "default@PackageHap",
          "taskPath": "entry",
          "workerId": 1,
          "startTime": 1700793184567
        }
      ],
      "name": "overallTime",
      "taskName": "default@PackageHap",
      "taskPath": "entry",
      "workerId": -1,
      "startTime": 1700793184566
    },
    {
      "type": "build_line",
      "endTime": 1700793184750,
      "status": "closed",
      "children": [],
      "name": "overallTime",
      "taskName": "default@SignHap",
      "taskPath": "entry",
      "workerId": -1,
      "startTime": 1700793184750
    },
    {
      "type": "build_line",
      "endTime": 1700793184751,
      "status": "closed",
      "children": [],
      "name": "overallTime",
      "taskName": "assembleHap",
      "taskPath": "entry",
      "workerId": -1,
      "startTime": 1700793184751
    },
    {
      "type": "build_line",
      "endTime": 1700793326979,
      "status": "closed",
      "children": [],
      "name": "overallTime",
      "taskName": "default@PreBuild",
      "taskPath": "entry",
      "workerId": -1,
      "startTime": 1700793326979
    },
    {
      "type": "build_line",
      "endTime": 1700793326981,
      "status": "closed",
      "children": [],
      "name": "overallTime",
      "taskName": "default@PreBuild",
      "taskPath": "common_lib",
      "workerId": -1,
      "startTime": 1700793326981
    },
    {
      "type": "build_line",
      "endTime": 1700793326985,
      "status": "closed",
      "children": [],
      "name": "overallTime",
      "taskName": "default@GenerateMetadata",
      "taskPath": "entry",
      "workerId": -1,
      "startTime": 1700793326982
    },
    {
      "type": "build_line",
      "endTime": 1700793326986,
      "status": "closed",
      "children": [],
      "name": "overallTime",
      "taskName": "default@BuildNativeWithCmake",
      "taskPath": "entry",
      "workerId": -1,
      "startTime": 1700793326986
    },
    {
      "type": "build_line",
      "endTime": 1700793326988,
      "status": "closed",
      "children": [],
      "name": "overallTime",
      "taskName": "default@GenerateLoaderJson",
      "taskPath": "entry",
      "workerId": -1,
      "startTime": 1700793326988
    },
    {
      "type": "build_line",
      "endTime": 1700793326989,
      "status": "closed",
      "children": [],
      "name": "overallTime",
      "taskName": "default@BuildNativeWithCmake",
      "taskPath": "common_lib",
      "workerId": -1,
      "startTime": 1700793326989
    },
    {
      "type": "build_line",
      "endTime": 1700793326991,
      "status": "closed",
      "children": [],
      "name": "overallTime",
      "taskName": "default@MergeProfile",
      "taskPath": "common_lib",
      "workerId": -1,
      "startTime": 1700793326990
    },
    {
      "type": "build_line",
      "endTime": 1700793326992,
      "status": "closed",
      "children": [],
      "name": "overallTime",
      "taskName": "default@BuildNativeWithNinja",
      "taskPath": "entry",
      "workerId": -1,
      "startTime": 1700793326992
    },
    {
      "type": "build_line",
      "endTime": 1700793326993,
      "status": "closed",
      "children": [],
      "name": "overallTime",
      "taskName": "default@BuildNativeWithNinja",
      "taskPath": "common_lib",
      "workerId": -1,
      "startTime": 1700793326993
    },
    {
      "type": "build_line",
      "endTime": 1700793326995,
      "status": "closed",
      "children": [],
      "name": "overallTime",
      "taskName": "default@MergeProfile",
      "taskPath": "entry",
      "workerId": -1,
      "startTime": 1700793326994
    },
    {
      "type": "build_line",
      "endTime": 1700793326995,
      "status": "closed",
      "children": [],
      "name": "overallTime",
      "taskName": "default@ProcessLibs",
      "taskPath": "common_lib",
      "workerId": -1,
      "startTime": 1700793326995
    },
    {
      "type": "build_line",
      "endTime": 1700793326999,
      "status": "closed",
      "children": [],
      "name": "overallTime",
      "taskName": "default@MakePackInfo",
      "taskPath": "entry",
      "workerId": -1,
      "startTime": 1700793326996
    },
    {
      "type": "build_line",
      "endTime": 1700793327001,
      "status": "closed",
      "children": [],
      "name": "overallTime",
      "taskName": "default@ProcessProfile",
      "taskPath": "entry",
      "workerId": -1,
      "startTime": 1700793327000
    },
    {
      "type": "build_line",
      "endTime": 1700793327002,
      "status": "closed",
      "children": [],
      "name": "overallTime",
      "taskName": "default@ProcessLibs",
      "taskPath": "entry",
      "workerId": -1,
      "startTime": 1700793327002
    },
    {
      "type": "build_line",
      "endTime": 1700793327004,
      "status": "closed",
      "children": [],
      "name": "overallTime",
      "taskName": "default@ProcessResource",
      "taskPath": "entry",
      "workerId": -1,
      "startTime": 1700793327003
    },
    {
      "type": "build_line",
      "endTime": 1700793327007,
      "status": "closed",
      "children": [],
      "name": "overallTime",
      "taskName": "default@CompileResource",
      "taskPath": "entry",
      "workerId": -1,
      "startTime": 1700793327004
    },
    {
      "type": "build_line",
      "endTime": 1700793327014,
      "status": "closed",
      "children": [],
      "name": "overallTime",
      "taskName": "default@CompileJS",
      "taskPath": "entry",
      "workerId": -1,
      "startTime": 1700793327012
    },
    {
      "type": "build_line",
      "endTime": 1700793328622,
      "status": "closed",
      "children": [],
      "name": "overallTime",
      "taskName": "default@CompileArkTS",
      "taskPath": "entry",
      "workerId": 0,
      "startTime": 1700793327012
    },
    {
      "type": "default",
      "endTime": 1700793328622,
      "status": "closed",
      "children": [
        {
          "type": "build_line",
          "endTime": 1700793328622,
          "status": "closed",
          "children": [],
          "name": "overallTime",
          "taskName": "default@CompileArkTS",
          "taskPath": "entry",
          "workerId": 0,
          "startTime": 1700793327012
        }
      ],
      "name": "overallTime",
      "taskName": "default@CompileArkTS",
      "taskPath": "entry",
      "workerId": -1,
      "startTime": 1700793327007
    },
    {
      "type": "build_line",
      "endTime": 1700793336023,
      "status": "closed",
      "children": [],
      "name": "overallTime",
      "taskName": "default@PreBuild",
      "taskPath": "entry",
      "workerId": -1,
      "startTime": 1700793336023
    },
    {
      "type": "build_line",
      "endTime": 1700793336025,
      "status": "closed",
      "children": [],
      "name": "overallTime",
      "taskName": "default@PreBuild",
      "taskPath": "common_lib",
      "workerId": -1,
      "startTime": 1700793336024
    },
    {
      "type": "build_line",
      "endTime": 1700793336031,
      "status": "closed",
      "children": [],
      "name": "overallTime",
      "taskName": "default@GenerateMetadata",
      "taskPath": "entry",
      "workerId": -1,
      "startTime": 1700793336026
    },
    {
      "type": "build_line",
      "endTime": 1700793336033,
      "status": "closed",
      "children": [],
      "name": "overallTime",
      "taskName": "default@BuildNativeWithCmake",
      "taskPath": "entry",
      "workerId": -1,
      "startTime": 1700793336033
    },
    {
      "type": "build_line",
      "endTime": 1700793336034,
      "status": "closed",
      "children": [],
      "name": "overallTime",
      "taskName": "default@GenerateLoaderJson",
      "taskPath": "entry",
      "workerId": -1,
      "startTime": 1700793336034
    },
    {
      "type": "build_line",
      "endTime": 1700793336035,
      "status": "closed",
      "children": [],
      "name": "overallTime",
      "taskName": "default@BuildNativeWithCmake",
      "taskPath": "common_lib",
      "workerId": -1,
      "startTime": 1700793336035
    },
    {
      "type": "build_line",
      "endTime": 1700793336036,
      "status": "closed",
      "children": [],
      "name": "overallTime",
      "taskName": "default@MergeProfile",
      "taskPath": "common_lib",
      "workerId": -1,
      "startTime": 1700793336036
    },
    {
      "type": "build_line",
      "endTime": 1700793336037,
      "status": "closed",
      "children": [],
      "name": "overallTime",
      "taskName": "default@BuildNativeWithNinja",
      "taskPath": "entry",
      "workerId": -1,
      "startTime": 1700793336037
    },
    {
      "type": "build_line",
      "endTime": 1700793336040,
      "status": "closed",
      "children": [],
      "name": "overallTime",
      "taskName": "default@BuildNativeWithNinja",
      "taskPath": "common_lib",
      "workerId": -1,
      "startTime": 1700793336040
    },
    {
      "type": "build_line",
      "endTime": 1700793336041,
      "status": "closed",
      "children": [],
      "name": "overallTime",
      "taskName": "default@MergeProfile",
      "taskPath": "entry",
      "workerId": -1,
      "startTime": 1700793336041
    },
    {
      "type": "build_line",
      "endTime": 1700793336045,
      "status": "closed",
      "children": [],
      "name": "overallTime",
      "taskName": "default@ProcessLibs",
      "taskPath": "common_lib",
      "workerId": -1,
      "startTime": 1700793336045
    },
    {
      "type": "build_line",
      "endTime": 1700793336049,
      "status": "closed",
      "children": [],
      "name": "overallTime",
      "taskName": "default@MakePackInfo",
      "taskPath": "entry",
      "workerId": -1,
      "startTime": 1700793336046
    },
    {
      "type": "build_line",
      "endTime": 1700793336050,
      "status": "closed",
      "children": [],
      "name": "overallTime",
      "taskName": "default@ProcessProfile",
      "taskPath": "entry",
      "workerId": -1,
      "startTime": 1700793336049
    },
    {
      "type": "build_line",
      "endTime": 1700793336050,
      "status": "closed",
      "children": [],
      "name": "overallTime",
      "taskName": "default@ProcessLibs",
      "taskPath": "entry",
      "workerId": -1,
      "startTime": 1700793336050
    },
    {
      "type": "build_line",
      "endTime": 1700793336052,
      "status": "closed",
      "children": [],
      "name": "overallTime",
      "taskName": "default@ProcessResource",
      "taskPath": "entry",
      "workerId": -1,
      "startTime": 1700793336051
    },
    {
      "type": "build_line",
      "endTime": 1700793336055,
      "status": "closed",
      "children": [],
      "name": "overallTime",
      "taskName": "default@CompileResource",
      "taskPath": "entry",
      "workerId": -1,
      "startTime": 1700793336052
    },
    {
      "type": "build_line",
      "endTime": 1700793336058,
      "status": "closed",
      "children": [],
      "name": "overallTime",
      "taskName": "default@CompileJS",
      "taskPath": "entry",
      "workerId": -1,
      "startTime": 1700793336057
    },
    {
      "type": "build_line",
      "endTime": 1700793337455,
      "status": "closed",
      "children": [],
      "name": "overallTime",
      "taskName": "default@CompileArkTS",
      "taskPath": "entry",
      "workerId": 0,
      "startTime": 1700793336057
    },
    {
      "type": "default",
      "endTime": 1700793337455,
      "status": "closed",
      "children": [
        {
          "type": "build_line",
          "endTime": 1700793337455,
          "status": "closed",
          "children": [],
          "name": "overallTime",
          "taskName": "default@CompileArkTS",
          "taskPath": "entry",
          "workerId": 0,
          "startTime": 1700793336057
        }
      ],
      "name": "overallTime",
      "taskName": "default@CompileArkTS",
      "taskPath": "entry",
      "workerId": -1,
      "startTime": 1700793336055
    },
    {
      "type": "build_line",
      "endTime": 1700793348377,
      "status": "closed",
      "children": [],
      "name": "overallTime",
      "taskName": "default@PreBuild",
      "taskPath": "entry",
      "workerId": -1,
      "startTime": 1700793348376
    },
    {
      "type": "build_line",
      "endTime": 1700793348378,
      "status": "closed",
      "children": [],
      "name": "overallTime",
      "taskName": "default@PreBuild",
      "taskPath": "common_lib",
      "workerId": -1,
      "startTime": 1700793348378
    },
    {
      "type": "build_line",
      "endTime": 1700793348381,
      "status": "closed",
      "children": [],
      "name": "overallTime",
      "taskName": "default@GenerateMetadata",
      "taskPath": "entry",
      "workerId": -1,
      "startTime": 1700793348379
    },
    {
      "type": "build_line",
      "endTime": 1700793348383,
      "status": "closed",
      "children": [],
      "name": "overallTime",
      "taskName": "default@BuildNativeWithCmake",
      "taskPath": "entry",
      "workerId": -1,
      "startTime": 1700793348383
    },
    {
      "type": "build_line",
      "endTime": 1700793348384,
      "status": "closed",
      "children": [],
      "name": "overallTime",
      "taskName": "default@GenerateLoaderJson",
      "taskPath": "entry",
      "workerId": -1,
      "startTime": 1700793348384
    },
    {
      "type": "build_line",
      "endTime": 1700793348385,
      "status": "closed",
      "children": [],
      "name": "overallTime",
      "taskName": "default@BuildNativeWithCmake",
      "taskPath": "common_lib",
      "workerId": -1,
      "startTime": 1700793348385
    },
    {
      "type": "build_line",
      "endTime": 1700793348387,
      "status": "closed",
      "children": [],
      "name": "overallTime",
      "taskName": "default@MergeProfile",
      "taskPath": "common_lib",
      "workerId": -1,
      "startTime": 1700793348387
    },
    {
      "type": "build_line",
      "endTime": 1700793348387,
      "status": "closed",
      "children": [],
      "name": "overallTime",
      "taskName": "default@BuildNativeWithNinja",
      "taskPath": "entry",
      "workerId": -1,
      "startTime": 1700793348387
    },
    {
      "type": "build_line",
      "endTime": 1700793348388,
      "status": "closed",
      "children": [],
      "name": "overallTime",
      "taskName": "default@BuildNativeWithNinja",
      "taskPath": "common_lib",
      "workerId": -1,
      "startTime": 1700793348388
    },
    {
      "type": "build_line",
      "endTime": 1700793348390,
      "status": "closed",
      "children": [],
      "name": "overallTime",
      "taskName": "default@MergeProfile",
      "taskPath": "entry",
      "workerId": -1,
      "startTime": 1700793348389
    },
    {
      "type": "build_line",
      "endTime": 1700793348391,
      "status": "closed",
      "children": [],
      "name": "overallTime",
      "taskName": "default@ProcessLibs",
      "taskPath": "common_lib",
      "workerId": -1,
      "startTime": 1700793348391
    },
    {
      "type": "build_line",
      "endTime": 1700793348393,
      "status": "closed",
      "children": [],
      "name": "overallTime",
      "taskName": "default@MakePackInfo",
      "taskPath": "entry",
      "workerId": -1,
      "startTime": 1700793348391
    },
    {
      "type": "build_line",
      "endTime": 1700793348395,
      "status": "closed",
      "children": [],
      "name": "overallTime",
      "taskName": "default@ProcessProfile",
      "taskPath": "entry",
      "workerId": -1,
      "startTime": 1700793348394
    },
    {
      "type": "build_line",
      "endTime": 1700793348396,
      "status": "closed",
      "children": [],
      "name": "overallTime",
      "taskName": "default@ProcessLibs",
      "taskPath": "entry",
      "workerId": -1,
      "startTime": 1700793348396
    },
    {
      "type": "build_line",
      "endTime": 1700793348397,
      "status": "closed",
      "children": [],
      "name": "overallTime",
      "taskName": "default@ProcessResource",
      "taskPath": "entry",
      "workerId": -1,
      "startTime": 1700793348396
    },
    {
      "type": "build_line",
      "endTime": 1700793348399,
      "status": "closed",
      "children": [],
      "name": "overallTime",
      "taskName": "default@CompileResource",
      "taskPath": "entry",
      "workerId": -1,
      "startTime": 1700793348398
    },
    {
      "type": "build_line",
      "endTime": 1700793348404,
      "status": "closed",
      "children": [],
      "name": "overallTime",
      "taskName": "default@CompileJS",
      "taskPath": "entry",
      "workerId": -1,
      "startTime": 1700793348403
    },
    {
      "type": "build_line",
      "endTime": 1700793349926,
      "status": "closed",
      "children": [],
      "name": "overallTime",
      "taskName": "default@CompileArkTS",
      "taskPath": "entry",
      "workerId": 0,
      "startTime": 1700793348403
    },
    {
      "type": "default",
      "endTime": 1700793349926,
      "status": "closed",
      "children": [
        {
          "type": "build_line",
          "endTime": 1700793349926,
          "status": "closed",
          "children": [],
          "name": "overallTime",
          "taskName": "default@CompileArkTS",
          "taskPath": "entry",
          "workerId": 0,
          "startTime": 1700793348403
        }
      ],
      "name": "overallTime",
      "taskName": "default@CompileArkTS",
      "taskPath": "entry",
      "workerId": -1,
      "startTime": 1700793348399
    },
    {
      "type": "build_line",
      "endTime": 1700793350439,
      "status": "closed",
      "children": [],
      "name": "overallTime",
      "taskName": "default@PackageHap",
      "taskPath": "entry",
      "workerId": 0,
      "startTime": 1700793350029
    },
    {
      "type": "default",
      "endTime": 1700793350439,
      "status": "closed",
      "children": [
        {
          "type": "build_line",
          "endTime": 1700793350439,
          "status": "closed",
          "children": [],
          "name": "overallTime",
          "taskName": "default@PackageHap",
          "taskPath": "entry",
          "workerId": 0,
          "startTime": 1700793350029
        }
      ],
      "name": "overallTime",
      "taskName": "default@PackageHap",
      "taskPath": "entry",
      "workerId": -1,
      "startTime": 1700793349929
    },
    {
      "type": "build_line",
      "endTime": 1700793350440,
      "status": "closed",
      "children": [],
      "name": "overallTime",
      "taskName": "default@SignHap",
      "taskPath": "entry",
      "workerId": -1,
      "startTime": 1700793350440
    },
    {
      "type": "build_line",
      "endTime": 1700793350442,
      "status": "closed",
      "children": [],
      "name": "overallTime",
      "taskName": "assembleHap",
      "taskPath": "entry",
      "workerId": -1,
      "startTime": 1700793350442
    },
    {
      "type": "build_line",
      "endTime": 1700794261917,
      "status": "closed",
      "children": [],
      "name": "overallTime",
      "taskName": "default@PreBuild",
      "taskPath": "entry",
      "workerId": -1,
      "startTime": 1700794261917
    },
    {
      "type": "build_line",
      "endTime": 1700794261920,
      "status": "closed",
      "children": [],
      "name": "overallTime",
      "taskName": "default@PreBuild",
      "taskPath": "common_lib",
      "workerId": -1,
      "startTime": 1700794261920
    },
    {
      "type": "build_line",
      "endTime": 1700794261927,
      "status": "closed",
      "children": [],
      "name": "overallTime",
      "taskName": "default@GenerateMetadata",
      "taskPath": "entry",
      "workerId": -1,
      "startTime": 1700794261922
    },
    {
      "type": "build_line",
      "endTime": 1700794261932,
      "status": "closed",
      "children": [],
      "name": "overallTime",
      "taskName": "default@BuildNativeWithCmake",
      "taskPath": "entry",
      "workerId": -1,
      "startTime": 1700794261932
    },
    {
      "type": "build_line",
      "endTime": 1700794261935,
      "status": "closed",
      "children": [],
      "name": "overallTime",
      "taskName": "default@GenerateLoaderJson",
      "taskPath": "entry",
      "workerId": -1,
      "startTime": 1700794261935
    },
    {
      "type": "build_line",
      "endTime": 1700794261935,
      "status": "closed",
      "children": [],
      "name": "overallTime",
      "taskName": "default@BuildNativeWithCmake",
      "taskPath": "common_lib",
      "workerId": -1,
      "startTime": 1700794261935
    },
    {
      "type": "build_line",
      "endTime": 1700794261937,
      "status": "closed",
      "children": [],
      "name": "overallTime",
      "taskName": "default@MergeProfile",
      "taskPath": "common_lib",
      "workerId": -1,
      "startTime": 1700794261937
    },
    {
      "type": "build_line",
      "endTime": 1700794261938,
      "status": "closed",
      "children": [],
      "name": "overallTime",
      "taskName": "default@BuildNativeWithNinja",
      "taskPath": "entry",
      "workerId": -1,
      "startTime": 1700794261938
    },
    {
      "type": "build_line",
      "endTime": 1700794261939,
      "status": "closed",
      "children": [],
      "name": "overallTime",
      "taskName": "default@BuildNativeWithNinja",
      "taskPath": "common_lib",
      "workerId": -1,
      "startTime": 1700794261939
    },
    {
      "type": "build_line",
      "endTime": 1700794261940,
      "status": "closed",
      "children": [],
      "name": "overallTime",
      "taskName": "default@MergeProfile",
      "taskPath": "entry",
      "workerId": -1,
      "startTime": 1700794261940
    },
    {
      "type": "build_line",
      "endTime": 1700794261941,
      "status": "closed",
      "children": [],
      "name": "overallTime",
      "taskName": "default@ProcessLibs",
      "taskPath": "common_lib",
      "workerId": -1,
      "startTime": 1700794261941
    },
    {
      "type": "build_line",
      "endTime": 1700794261944,
      "status": "closed",
      "children": [],
      "name": "overallTime",
      "taskName": "default@MakePackInfo",
      "taskPath": "entry",
      "workerId": -1,
      "startTime": 1700794261942
    },
    {
      "type": "build_line",
      "endTime": 1700794261945,
      "status": "closed",
      "children": [],
      "name": "overallTime",
      "taskName": "default@ProcessProfile",
      "taskPath": "entry",
      "workerId": -1,
      "startTime": 1700794261945
    },
    {
      "type": "build_line",
      "endTime": 1700794261947,
      "status": "closed",
      "children": [],
      "name": "overallTime",
      "taskName": "default@ProcessLibs",
      "taskPath": "entry",
      "workerId": -1,
      "startTime": 1700794261947
    },
    {
      "type": "build_line",
      "endTime": 1700794261949,
      "status": "closed",
      "children": [],
      "name": "overallTime",
      "taskName": "default@ProcessResource",
      "taskPath": "entry",
      "workerId": -1,
      "startTime": 1700794261948
    },
    {
      "type": "build_line",
      "endTime": 1700794261951,
      "status": "closed",
      "children": [],
      "name": "overallTime",
      "taskName": "default@CompileResource",
      "taskPath": "entry",
      "workerId": -1,
      "startTime": 1700794261949
    },
    {
      "type": "build_line",
      "endTime": 1700794261958,
      "status": "closed",
      "children": [],
      "name": "overallTime",
      "taskName": "default@CompileJS",
      "taskPath": "entry",
      "workerId": -1,
      "startTime": 1700794261957
    },
    {
      "type": "build_line",
      "endTime": 1700794263557,
      "status": "closed",
      "children": [],
      "name": "overallTime",
      "taskName": "default@CompileArkTS",
      "taskPath": "entry",
      "workerId": 2,
      "startTime": 1700794261957
    },
    {
      "type": "default",
      "endTime": 1700794263557,
      "status": "closed",
      "children": [
        {
          "type": "build_line",
          "endTime": 1700794263557,
          "status": "closed",
          "children": [],
          "name": "overallTime",
          "taskName": "default@CompileArkTS",
          "taskPath": "entry",
          "workerId": 2,
          "startTime": 1700794261957
        }
      ],
      "name": "overallTime",
      "taskName": "default@CompileArkTS",
      "taskPath": "entry",
      "workerId": -1,
      "startTime": 1700794261951
    },
    {
      "type": "build_line",
      "endTime": 1700794264114,
      "status": "closed",
      "children": [],
      "name": "overallTime",
      "taskName": "default@PackageHap",
      "taskPath": "entry",
      "workerId": 2,
      "startTime": 1700794263659
    },
    {
      "type": "default",
      "endTime": 1700794264114,
      "status": "closed",
      "children": [
        {
          "type": "build_line",
          "endTime": 1700794264114,
          "status": "closed",
          "children": [],
          "name": "overallTime",
          "taskName": "default@PackageHap",
          "taskPath": "entry",
          "workerId": 2,
          "startTime": 1700794263659
        }
      ],
      "name": "overallTime",
      "taskName": "default@PackageHap",
      "taskPath": "entry",
      "workerId": -1,
      "startTime": 1700794263559
    },
    {
      "type": "build_line",
      "endTime": 1700794264115,
      "status": "closed",
      "children": [],
      "name": "overallTime",
      "taskName": "default@SignHap",
      "taskPath": "entry",
      "workerId": -1,
      "startTime": 1700794264115
    },
    {
      "type": "build_line",
      "endTime": 1700794264116,
      "status": "closed",
      "children": [],
      "name": "overallTime",
      "taskName": "assembleHap",
      "taskPath": "entry",
      "workerId": -1,
      "startTime": 1700794264116
    }
  ],
  "workLog": []
}